setup.py
distributions_hs/Binomialdistribution.py
distributions_hs/Gaussiandistribution.py
distributions_hs/Generaldistribution.py
distributions_hs/__init__.py
distributions_hs.egg-info/PKG-INFO
distributions_hs.egg-info/SOURCES.txt
distributions_hs.egg-info/dependency_links.txt
distributions_hs.egg-info/not-zip-safe
distributions_hs.egg-info/top_level.txt