Metadata-Version: 1.0
Name: distributions-hs
Version: 0.1
Summary: Gaussian & Binomial distributions
Home-page: UNKNOWN
Author: Hamed Salooti
Author-email: hamed.salooti@gmail.com
License: UNKNOWN
Platform: UNKNOWN
